openg2p_g2p_bridge_bank_connectors/__init__.py
openg2p_g2p_bridge_bank_connectors/app.py
openg2p_g2p_bridge_bank_connectors/config.py
openg2p_g2p_bridge_bank_connectors/bank_connectors/__init__.py
openg2p_g2p_bridge_bank_connectors/bank_connectors/bank_connector_factory.py
openg2p_g2p_bridge_bank_connectors/bank_connectors/example_bank_connector.py
openg2p_g2p_bridge_bank_connectors/bank_interface/__init__.py
openg2p_g2p_bridge_bank_connectors/bank_interface/bank_connector_interface.py
openg2p_g2p_bridge_bank_connectors-1.1.0.dist-info/METADATA
openg2p_g2p_bridge_bank_connectors-1.1.0.dist-info/WHEEL
openg2p_g2p_bridge_bank_connectors-1.1.0.dist-info/RECORD
